{
  "@context": "http://schema.org",
  "@type": "CreditCard",
  "additionalType": "Daggernarrow",
  "aggregateRating": {
    "@type": "AggregateRating",
    "itemReviewed": null,
    "ratingCount": 84,
    "reviewCount": 10
  },
  "alternateName": "Scribeprickle",
  "amount": {
    "@type": "MonetaryAmount",
    "currency": "Kangarooproud",
    "maxValue": 86,
    "minValue": 78,
    "validFrom": "2008-05-29T04:20",
    "validThrough": "2001-06-10T20:36",
    "value": true
  },
  "annualPercentageRate": 36,
  "areaServed": {
    "@type": "AdministrativeArea",
    "additionalProperty": null,
    "address": null,
    "aggregateRating": null,
    "amenityFeature": null,
    "branchCode": "Rayapple",
    "containedInPlace": null,
    "containsPlace": null,
    "event": null,
    "faxNumber": "Rabbitrowan",
    "geo": null,
    "geospatiallyContains": null,
    "geospatiallyCoveredBy": null,
    "geospatiallyCovers": null,
    "geospatiallyCrosses": null,
    "geospatiallyDisjoint": null,
    "geospatiallyEquals": null,
    "geospatiallyIntersects": null,
    "geospatiallyOverlaps": null,
    "geospatiallyTouches": null,
    "geospatiallyWithin": null,
    "globalLocationNumber": "Guardianbutter",
    "hasMap": null,
    "isAccessibleForFree": false,
    "isicV4": "Racerrune",
    "logo": null,
    "maximumAttendeeCapacity": 53,
    "openingHoursSpecification": null,
    "photo": null,
    "publicAccess": false,
    "review": null,
    "smokingAllowed": true,
    "specialOpeningHoursSpecification": null,
    "telephone": "Ringerash"
  },
  "audience": {
    "@type": "Audience",
    "audienceType": "Facenettle",
    "geographicArea": null
  },
  "availableChannel": {
    "@type": "ServiceChannel",
    "availableLanguage": null,
    "processingTime": null,
    "providesService": null,
    "serviceLocation": null,
    "servicePhone": null,
    "servicePostalAddress": null,
    "serviceSmsNumber": null,
    "serviceUrl": "Chanterivory"
  },
  "award": "Houndmica",
  "brand": {
    "@type": "Brand"
  },
  "broker": {
    "@type": "Organization",
    "actionableFeedbackPolicy": null,
    "address": null,
    "aggregateRating": null,
    "alumni": null,
    "areaServed": null,
    "award": "Salmonpattern",
    "brand": null,
    "contactPoint": null,
    "correctionsPolicy": null,
    "department": null,
    "dissolutionDate": "1989-09-13",
    "diversityPolicy": null,
    "duns": "Finquill",
    "email": "Skinnerlight",
    "employee": null,
    "ethicsPolicy": null,
    "event": null,
    "faxNumber": "Spikevanilla",
    "founder": null,
    "foundingDate": "1984-11-07",
    "foundingLocation": null,
    "funder": null,
    "globalLocationNumber": "Jawpink",
    "hasOfferCatalog": null,
    "hasPOS": null,
    "isicV4": "Hawkpear",
    "legalName": "Chatterflame",
    "leiCode": "Salmonrogue",
    "location": null,
    "logo": null,
    "makesOffer": null,
    "member": null,
    "memberOf": null,
    "naics": "Runnermire",
    "numberOfEmployees": null,
    "owns": null,
    "parentOrganization": null,
    "publishingPrinciples": null,
    "review": null,
    "seeks": null,
    "sponsor": null,
    "subOrganization": null,
    "taxID": "Houndgossamer",
    "telephone": "Crownquartz",
    "unnamedSourcesPolicy": null,
    "vatID": "Centaurberry"
  },
  "category": null,
  "currency": "Leglove",
  "description": "Knavecotton",
  "disambiguatingDescription": "Mustangjuniper",
  "feesAndCommissionsSpecification": "Crafterink",
  "gracePeriod": {
    "@type": "Duration",
    "additionalType": "Leopardmulberry",
    "alternateName": "Wandererdiamond",
    "description": "Keeperdour",
    "disambiguatingDescription": "Mindalabaster",
    "identifier": null,
    "image": null,
    "mainEntityOfPage": null,
    "name": "Snappermica",
    "potentialAction": null,
    "sameAs": "Slavepalm",
    "url": "Moosetopaz"
  },
  "hasOfferCatalog": {
    "@type": "OfferCatalog",
    "itemListElement": null,
    "itemListOrder": null,
    "numberOfItems": 60
  },
  "hoursAvailable": {
    "@type": "OpeningHoursSpecification",
    "closes": "2003-06-03T20:18",
    "dayOfWeek": null,
    "opens": "1999-10-27T23:12",
    "validFrom": "2001-05-12T20:32",
    "validThrough": "1982-01-28T12:24"
  },
  "identifier": {
    "@type": "PropertyValue",
    "maxValue": 87,
    "measurementTechnique": "Jaytreasure",
    "minValue": 81,
    "propertyID": "Otterrampant",
    "unitCode": "Daggerquick",
    "unitText": "Frillgrave",
    "value": true,
    "valueReference": null
  },
  "image": {
    "@type": "ImageObject",
    "caption": "Beedark",
    "exifData": null,
    "representativeOfPage": true,
    "thumbnail": null
  },
  "interestRate": 33,
  "isRelatedTo": {
    "@type": "Product",
    "additionalProperty": null,
    "aggregateRating": null,
    "audience": null,
    "award": "Leadersequoia",
    "brand": null,
    "category": null,
    "color": "Napesavage",
    "depth": null,
    "gtin12": "Fishharvest",
    "gtin13": "Ringersapphire",
    "gtin14": "Ocelotrune",
    "gtin8": "Gullash",
    "height": null,
    "isAccessoryOrSparePartFor": null,
    "isConsumableFor": null,
    "isRelatedTo": null,
    "isSimilarTo": null,
    "itemCondition": null,
    "logo": null,
    "manufacturer": null,
    "material": null,
    "model": null,
    "mpn": "Stingertyphoon",
    "offers": null,
    "productID": "Spidertopaz",
    "productionDate": "1999-10-26",
    "purchaseDate": "1976-08-29",
    "releaseDate": "2017-09-18",
    "review": null,
    "sku": "Stingersleet",
    "weight": null,
    "width": null
  },
  "isSimilarTo": {
    "@type": "Product",
    "additionalProperty": null,
    "aggregateRating": null,
    "audience": null,
    "award": "Kangaroofancy",
    "brand": null,
    "category": null,
    "color": "Wyrmprairie",
    "depth": null,
    "gtin12": "Mythrainbow",
    "gtin13": "Seedmercury",
    "gtin14": "Minnowrag",
    "gtin8": "Killersharp",
    "height": null,
    "isAccessoryOrSparePartFor": null,
    "isConsumableFor": null,
    "isRelatedTo": null,
    "isSimilarTo": null,
    "itemCondition": null,
    "logo": null,
    "manufacturer": null,
    "material": null,
    "model": null,
    "mpn": "Thornwild",
    "offers": null,
    "productID": "Scarercoffee",
    "productionDate": "1982-08-30",
    "purchaseDate": "1980-03-07",
    "releaseDate": "2012-12-16",
    "review": null,
    "sku": "Iguanaslow",
    "weight": null,
    "width": null
  },
  "loanRepaymentForm": null,
  "loanTerm": {
    "@type": "QuantitativeValue",
    "additionalProperty": null,
    "maxValue": 53,
    "minValue": 95,
    "unitCode": "Volefeather",
    "unitText": "Knightnavy",
    "value": true,
    "valueReference": null
  },
  "loanType": "Cranelunar",
  "logo": {
    "@type": "ImageObject",
    "caption": "Goatcherry",
    "exifData": null,
    "representativeOfPage": false,
    "thumbnail": null
  },
  "mainEntityOfPage": {
    "@type": "CreativeWork",
    "about": null,
    "accessMode": "Sighthurricane",
    "accessModeSufficient": "Seedpsychadelic",
    "accessibilityAPI": "Divehelix",
    "accessibilityControl": "Lifterthorn",
    "accessibilityFeature": "Ribpatch",
    "accessibilityHazard": "Fishsunset",
    "accessibilitySummary": "Shieldmorning",
    "accountablePerson": null,
    "aggregateRating": null,
    "alternativeHeadline": "Jaynight",
    "associatedMedia": null,
    "audience": null,
    "audio": null,
    "author": null,
    "award": "Speakerhorn",
    "character": null,
    "citation": null,
    "comment": null,
    "commentCount": 4,
    "contentLocation": null,
    "contentRating": "Roarerscarlet",
    "contentReferenceTime": "1985-04-14T08:45",
    "contributor": null,
    "copyrightHolder": null,
    "copyrightYear": 69,
    "creator": null,
    "dateCreated": "2017-05-28",
    "dateModified": "2008-07-28",
    "datePublished": "1983-09-09",
    "discussionUrl": "Dogchain",
    "editor": null,
    "educationalAlignment": null,
    "educationalUse": "Jawjungle",
    "encoding": null,
    "exampleOfWork": null,
    "expires": "1994-02-26",
    "fileFormat": "Ravenjust",
    "funder": null,
    "genre": "Toothjelly",
    "hasPart": null,
    "headline": "Wizarddour",
    "inLanguage": null,
    "interactionStatistic": null,
    "interactivityType": "Seersage",
    "isAccessibleForFree": false,
    "isBasedOn": null,
    "isFamilyFriendly": false,
    "isPartOf": null,
    "keywords": "Scorpiondandy",
    "learningResourceType": "Weedbevel",
    "license": null,
    "locationCreated": null,
    "mainEntity": null,
    "material": null,
    "mentions": null,
    "offers": null,
    "position": 7,
    "producer": null,
    "provider": null,
    "publication": null,
    "publisher": null,
    "publisherImprint": null,
    "publishingPrinciples": null,
    "recordedAt": null,
    "releasedEvent": null,
    "review": null,
    "schemaVersion": "Watcherkiwi",
    "sourceOrganization": null,
    "spatialCoverage": null,
    "sponsor": null,
    "temporalCoverage": "1984-12-06T18:04",
    "text": "Huggerroan",
    "thumbnailUrl": "Seekerpolar",
    "timeRequired": null,
    "translationOfWork": null,
    "translator": null,
    "typicalAgeRange": "Beebrass",
    "version": 82,
    "video": null,
    "workExample": null,
    "workTranslation": null
  },
  "monthlyMinimumRepaymentAmount": {
    "@type": "MonetaryAmount",
    "currency": "Apemesquite",
    "maxValue": 43,
    "minValue": 7,
    "validFrom": "2001-06-24T09:18",
    "validThrough": "1995-07-26T23:55",
    "value": true
  },
  "name": "Scarerfuschia",
  "offers": {
    "@type": "Offer",
    "acceptedPaymentMethod": null,
    "addOn": null,
    "advanceBookingRequirement": null,
    "aggregateRating": null,
    "areaServed": null,
    "availability": null,
    "availabilityEnds": "2007-01-23T17:54",
    "availabilityStarts": "1974-01-28T06:18",
    "availableAtOrFrom": null,
    "availableDeliveryMethod": null,
    "businessFunction": null,
    "category": null,
    "deliveryLeadTime": null,
    "eligibleCustomerType": null,
    "eligibleDuration": null,
    "eligibleQuantity": null,
    "eligibleRegion": null,
    "eligibleTransactionVolume": null,
    "gtin12": "Baneslash",
    "gtin13": "Puppycypress",
    "gtin14": "Handclear",
    "gtin8": "Bolttitanium",
    "includesObject": null,
    "ineligibleRegion": null,
    "inventoryLevel": null,
    "itemCondition": null,
    "itemOffered": null,
    "mpn": "Diverchisel",
    "offeredBy": null,
    "price": 3,
    "priceCurrency": "Napeyellow",
    "priceSpecification": null,
    "priceValidUntil": "1971-01-14",
    "review": null,
    "seller": null,
    "serialNumber": "Hawkmoor",
    "sku": "Sageshore",
    "validFrom": "1980-02-16T13:05",
    "validThrough": "1972-11-17T17:09",
    "warranty": null
  },
  "potentialAction": {
    "@type": "Action",
    "actionStatus": null,
    "agent": null,
    "endTime": "1992-11-03T01:57",
    "error": null,
    "instrument": null,
    "location": null,
    "object": null,
    "participant": null,
    "result": null,
    "startTime": "1975-07-22T03:28",
    "target": null
  },
  "provider": {
    "@type": "Organization",
    "actionableFeedbackPolicy": null,
    "address": null,
    "aggregateRating": null,
    "alumni": null,
    "areaServed": null,
    "award": "Crestvolcano",
    "brand": null,
    "contactPoint": null,
    "correctionsPolicy": null,
    "department": null,
    "dissolutionDate": "1974-07-12",
    "diversityPolicy": null,
    "duns": "Scarripple",
    "email": "Trackphase",
    "employee": null,
    "ethicsPolicy": null,
    "event": null,
    "faxNumber": "Duckmeteor",
    "founder": null,
    "foundingDate": "2008-12-27",
    "foundingLocation": null,
    "funder": null,
    "globalLocationNumber": "Rabbitdisco",
    "hasOfferCatalog": null,
    "hasPOS": null,
    "isicV4": "Heropattern",
    "legalName": "Leaderprong",
    "leiCode": "Hidejasper",
    "location": null,
    "logo": null,
    "makesOffer": null,
    "member": null,
    "memberOf": null,
    "naics": "Followercrocus",
    "numberOfEmployees": null,
    "owns": null,
    "parentOrganization": null,
    "publishingPrinciples": null,
    "review": null,
    "seeks": null,
    "sponsor": null,
    "subOrganization": null,
    "taxID": "Dutchessmaze",
    "telephone": "Dukerose",
    "unnamedSourcesPolicy": null,
    "vatID": "Serpentgreat"
  },
  "providerMobility": "Mustangstar",
  "recourseLoan": false,
  "renegotiableLoan": false,
  "requiredCollateral": "Watcherweed",
  "review": {
    "@type": "Review",
    "itemReviewed": null,
    "reviewBody": "Capgreat",
    "reviewRating": null
  },
  "sameAs": "Rabbitdaffodil",
  "serviceOutput": {
    "@type": "Thing",
    "additionalType": "Weedbald",
    "alternateName": "Gazelleapricot",
    "description": "Paladinlizard",
    "disambiguatingDescription": "Gemtree",
    "identifier": null,
    "image": null,
    "mainEntityOfPage": null,
    "name": "Singergem",
    "potentialAction": null,
    "sameAs": "Cloaknorth",
    "url": "Kickerfossil"
  },
  "serviceType": "Seerriver",
  "termsOfService": "Raypollen",
  "url": "Kickerforest"
}
