{
  "@context": "http://schema.org",
  "@type": "RegisterAction",
  "actionStatus": {
    "@type": "ActionStatusType",
    "supersededBy": null
  },
  "additionalType": "Toothplaid",
  "agent": {
    "@type": "Organization",
    "actionableFeedbackPolicy": null,
    "address": null,
    "aggregateRating": null,
    "alumni": null,
    "areaServed": null,
    "award": "Lighterviridian",
    "brand": null,
    "contactPoint": null,
    "correctionsPolicy": null,
    "department": null,
    "dissolutionDate": "1970-09-23",
    "diversityPolicy": null,
    "duns": "Ocelotpitch",
    "email": "Choppercoal",
    "employee": null,
    "ethicsPolicy": null,
    "event": null,
    "faxNumber": "Heronthread",
    "founder": null,
    "foundingDate": "1998-06-30",
    "foundingLocation": null,
    "funder": null,
    "globalLocationNumber": "Gargoylequilt",
    "hasOfferCatalog": null,
    "hasPOS": null,
    "isicV4": "Glassbush",
    "legalName": "Eaterquartz",
    "leiCode": "Snarlband",
    "location": null,
    "logo": null,
    "makesOffer": null,
    "member": null,
    "memberOf": null,
    "naics": "Forgerprism",
    "numberOfEmployees": null,
    "owns": null,
    "parentOrganization": null,
    "publishingPrinciples": null,
    "review": null,
    "seeks": null,
    "sponsor": null,
    "subOrganization": null,
    "taxID": "Ferretsplash",
    "telephone": "Hunterplaid",
    "unnamedSourcesPolicy": null,
    "vatID": "Questerjuniper"
  },
  "alternateName": "Koalagreen",
  "description": "Zebrawild",
  "disambiguatingDescription": "Arrowpale",
  "endTime": "1981-10-15T22:27",
  "error": {
    "@type": "Thing",
    "additionalType": "Lynxbrown",
    "alternateName": "Maskglass",
    "description": "Pigspangle",
    "disambiguatingDescription": "Handbald",
    "identifier": null,
    "image": null,
    "mainEntityOfPage": null,
    "name": "Snapperalabaster",
    "potentialAction": null,
    "sameAs": "Shirtsunset",
    "url": "Shriekerjewel"
  },
  "identifier": {
    "@type": "PropertyValue",
    "maxValue": 46,
    "measurementTechnique": "Dancerdawn",
    "minValue": 80,
    "propertyID": "Takerpebble",
    "unitCode": "Razorvine",
    "unitText": "Binderarrow",
    "value": true,
    "valueReference": null
  },
  "image": {
    "@type": "ImageObject",
    "caption": "Takertreasure",
    "exifData": null,
    "representativeOfPage": false,
    "thumbnail": null
  },
  "instrument": {
    "@type": "Thing",
    "additionalType": "Baneheather",
    "alternateName": "Gemshallow",
    "description": "Swoopstripe",
    "disambiguatingDescription": "Spriteviridian",
    "identifier": null,
    "image": null,
    "mainEntityOfPage": null,
    "name": "Falconbead",
    "potentialAction": null,
    "sameAs": "Reaperheavy",
    "url": "Stallionprism"
  },
  "location": {
    "@type": "Place",
    "additionalProperty": null,
    "address": null,
    "aggregateRating": null,
    "amenityFeature": null,
    "branchCode": "Burnvoid",
    "containedInPlace": null,
    "containsPlace": null,
    "event": null,
    "faxNumber": "Bearpeat",
    "geo": null,
    "geospatiallyContains": null,
    "geospatiallyCoveredBy": null,
    "geospatiallyCovers": null,
    "geospatiallyCrosses": null,
    "geospatiallyDisjoint": null,
    "geospatiallyEquals": null,
    "geospatiallyIntersects": null,
    "geospatiallyOverlaps": null,
    "geospatiallyTouches": null,
    "geospatiallyWithin": null,
    "globalLocationNumber": "Darthoney",
    "hasMap": null,
    "isAccessibleForFree": true,
    "isicV4": "Trackquasar",
    "logo": null,
    "maximumAttendeeCapacity": 30,
    "openingHoursSpecification": null,
    "photo": null,
    "publicAccess": true,
    "review": null,
    "smokingAllowed": false,
    "specialOpeningHoursSpecification": null,
    "telephone": "Palmsalt"
  },
  "mainEntityOfPage": {
    "@type": "CreativeWork",
    "about": null,
    "accessMode": "Rabbitfate",
    "accessModeSufficient": "Loonrapid",
    "accessibilityAPI": "Riderrose",
    "accessibilityControl": "Biterdot",
    "accessibilityFeature": "Collarpie",
    "accessibilityHazard": "Ladywinter",
    "accessibilitySummary": "Ravertrail",
    "accountablePerson": null,
    "aggregateRating": null,
    "alternativeHeadline": "Deermuck",
    "associatedMedia": null,
    "audience": null,
    "audio": null,
    "author": null,
    "award": "Divefair",
    "character": null,
    "citation": null,
    "comment": null,
    "commentCount": 68,
    "contentLocation": null,
    "contentRating": "Daggerquick",
    "contentReferenceTime": "1978-11-21T07:31",
    "contributor": null,
    "copyrightHolder": null,
    "copyrightYear": 66,
    "creator": null,
    "dateCreated": "2017-12-12",
    "dateModified": "2005-09-06",
    "datePublished": "1993-11-11",
    "discussionUrl": "Panthermaple",
    "editor": null,
    "educationalAlignment": null,
    "educationalUse": "Cowlfancy",
    "encoding": null,
    "exampleOfWork": null,
    "expires": "2014-10-24",
    "fileFormat": "Grabberbranch",
    "funder": null,
    "genre": "Napepolar",
    "hasPart": null,
    "headline": "Beered",
    "inLanguage": null,
    "interactionStatistic": null,
    "interactivityType": "Chestjungle",
    "isAccessibleForFree": false,
    "isBasedOn": null,
    "isFamilyFriendly": true,
    "isPartOf": null,
    "keywords": "Heronbloom",
    "learningResourceType": "Kangaroorune",
    "license": null,
    "locationCreated": null,
    "mainEntity": null,
    "material": null,
    "mentions": null,
    "offers": null,
    "position": 1,
    "producer": null,
    "provider": null,
    "publication": null,
    "publisher": null,
    "publisherImprint": null,
    "publishingPrinciples": null,
    "recordedAt": null,
    "releasedEvent": null,
    "review": null,
    "schemaVersion": "Chestalpine",
    "sourceOrganization": null,
    "spatialCoverage": null,
    "sponsor": null,
    "temporalCoverage": "2012-03-30T04:23",
    "text": "Bunnywell",
    "thumbnailUrl": "Skinnerkiwi",
    "timeRequired": null,
    "translationOfWork": null,
    "translator": null,
    "typicalAgeRange": "Slayerchocolate",
    "version": 97,
    "video": null,
    "workExample": null,
    "workTranslation": null
  },
  "name": "Chillpool",
  "object": {
    "@type": "Thing",
    "additionalType": "Chillbrown",
    "alternateName": "Slaveblaze",
    "description": "Voicemangrove",
    "disambiguatingDescription": "Touchrowan",
    "identifier": null,
    "image": null,
    "mainEntityOfPage": null,
    "name": "Storkcat",
    "potentialAction": null,
    "sameAs": "Slicerspangle",
    "url": "Geckotranslucent"
  },
  "participant": {
    "@type": "Organization",
    "actionableFeedbackPolicy": null,
    "address": null,
    "aggregateRating": null,
    "alumni": null,
    "areaServed": null,
    "award": "Sharkdew",
    "brand": null,
    "contactPoint": null,
    "correctionsPolicy": null,
    "department": null,
    "dissolutionDate": "1989-06-02",
    "diversityPolicy": null,
    "duns": "Giverfringe",
    "email": "Snarlripple",
    "employee": null,
    "ethicsPolicy": null,
    "event": null,
    "faxNumber": "Ringersolstice",
    "founder": null,
    "foundingDate": "2015-09-06",
    "foundingLocation": null,
    "funder": null,
    "globalLocationNumber": "Soarerglimmer",
    "hasOfferCatalog": null,
    "hasPOS": null,
    "isicV4": "Birdstitch",
    "legalName": "Herolunar",
    "leiCode": "Ocelotyellow",
    "location": null,
    "logo": null,
    "makesOffer": null,
    "member": null,
    "memberOf": null,
    "naics": "Friendcrimson",
    "numberOfEmployees": null,
    "owns": null,
    "parentOrganization": null,
    "publishingPrinciples": null,
    "review": null,
    "seeks": null,
    "sponsor": null,
    "subOrganization": null,
    "taxID": "Wolfpolar",
    "telephone": "Runnercoral",
    "unnamedSourcesPolicy": null,
    "vatID": "Ferretivory"
  },
  "potentialAction": {
    "@type": "Action",
    "actionStatus": null,
    "agent": null,
    "endTime": "2004-09-06T11:17",
    "error": null,
    "instrument": null,
    "location": null,
    "object": null,
    "participant": null,
    "result": null,
    "startTime": "2017-07-20T06:23",
    "target": null
  },
  "result": {
    "@type": "Thing",
    "additionalType": "Scaledew",
    "alternateName": "Runnerspangle",
    "description": "Dogmaple",
    "disambiguatingDescription": "Donkeydew",
    "identifier": null,
    "image": null,
    "mainEntityOfPage": null,
    "name": "Shakerslow",
    "potentialAction": null,
    "sameAs": "Seedlace",
    "url": "Kittenpaper"
  },
  "sameAs": "Jaguarpond",
  "startTime": "1976-03-25T00:50",
  "target": {
    "@type": "EntryPoint",
    "actionApplication": null,
    "actionPlatform": "Elfobsidian",
    "contentType": "Cattwisty",
    "encodingType": "Snarlflannel",
    "httpMethod": "Singerplump",
    "urlTemplate": "Llamacedar"
  },
  "url": "Molemotley"
}
