{
  "@context": "http://schema.org",
  "@type": "RejectAction",
  "actionStatus": {
    "@type": "ActionStatusType",
    "supersededBy": null
  },
  "additionalType": "Stalkerprairie",
  "agent": {
    "@type": "Organization",
    "actionableFeedbackPolicy": null,
    "address": null,
    "aggregateRating": null,
    "alumni": null,
    "areaServed": null,
    "award": "Servantsilent",
    "brand": null,
    "contactPoint": null,
    "correctionsPolicy": null,
    "department": null,
    "dissolutionDate": "1983-12-02",
    "diversityPolicy": null,
    "duns": "Spiritgrass",
    "email": "Boarwater",
    "employee": null,
    "ethicsPolicy": null,
    "event": null,
    "faxNumber": "Wingsponge",
    "founder": null,
    "foundingDate": "1994-02-04",
    "foundingLocation": null,
    "funder": null,
    "globalLocationNumber": "Lightermesquite",
    "hasOfferCatalog": null,
    "hasPOS": null,
    "isicV4": "Legfrill",
    "legalName": "Bitersnapdragon",
    "leiCode": "Carveratom",
    "location": null,
    "logo": null,
    "makesOffer": null,
    "member": null,
    "memberOf": null,
    "naics": "Batstone",
    "numberOfEmployees": null,
    "owns": null,
    "parentOrganization": null,
    "publishingPrinciples": null,
    "review": null,
    "seeks": null,
    "sponsor": null,
    "subOrganization": null,
    "taxID": "Guardianshell",
    "telephone": "Stealercrocus",
    "unnamedSourcesPolicy": null,
    "vatID": "Gemsolar"
  },
  "alternateName": "Stingerhorse",
  "description": "Huntercat",
  "disambiguatingDescription": "Browglass",
  "endTime": "2016-03-10T16:54",
  "error": {
    "@type": "Thing",
    "additionalType": "Boaremerald",
    "alternateName": "Oriolequark",
    "description": "Slothplaid",
    "disambiguatingDescription": "Snarloil",
    "identifier": null,
    "image": null,
    "mainEntityOfPage": null,
    "name": "Trackkiwi",
    "potentialAction": null,
    "sameAs": "Winghate",
    "url": "Wanderergeode"
  },
  "identifier": {
    "@type": "PropertyValue",
    "maxValue": 56,
    "measurementTechnique": "Thornflax",
    "minValue": 30,
    "propertyID": "Bonecotton",
    "unitCode": "Razorlavender",
    "unitText": "Dancerevening",
    "value": false,
    "valueReference": null
  },
  "image": {
    "@type": "ImageObject",
    "caption": "Jaguarpalm",
    "exifData": null,
    "representativeOfPage": true,
    "thumbnail": null
  },
  "instrument": {
    "@type": "Thing",
    "additionalType": "Molejelly",
    "alternateName": "Devourervoid",
    "description": "Shoulderfancy",
    "disambiguatingDescription": "Lizardflame",
    "identifier": null,
    "image": null,
    "mainEntityOfPage": null,
    "name": "Falcondaffodil",
    "potentialAction": null,
    "sameAs": "Talonlong",
    "url": "Ninjatar"
  },
  "location": {
    "@type": "Place",
    "additionalProperty": null,
    "address": null,
    "aggregateRating": null,
    "amenityFeature": null,
    "branchCode": "Slothjuniper",
    "containedInPlace": null,
    "containsPlace": null,
    "event": null,
    "faxNumber": "Singercyber",
    "geo": null,
    "geospatiallyContains": null,
    "geospatiallyCoveredBy": null,
    "geospatiallyCovers": null,
    "geospatiallyCrosses": null,
    "geospatiallyDisjoint": null,
    "geospatiallyEquals": null,
    "geospatiallyIntersects": null,
    "geospatiallyOverlaps": null,
    "geospatiallyTouches": null,
    "geospatiallyWithin": null,
    "globalLocationNumber": "Gemchestnut",
    "hasMap": null,
    "isAccessibleForFree": false,
    "isicV4": "Skinnerrhinestone",
    "logo": null,
    "maximumAttendeeCapacity": 67,
    "openingHoursSpecification": null,
    "photo": null,
    "publicAccess": true,
    "review": null,
    "smokingAllowed": true,
    "specialOpeningHoursSpecification": null,
    "telephone": "Lordwool"
  },
  "mainEntityOfPage": {
    "@type": "CreativeWork",
    "about": null,
    "accessMode": "Ravenseed",
    "accessModeSufficient": "Jawholly",
    "accessibilityAPI": "Crystalseason",
    "accessibilityControl": "Collarfoam",
    "accessibilityFeature": "Keepercookie",
    "accessibilityHazard": "Gorillawild",
    "accessibilitySummary": "Shifthorn",
    "accountablePerson": null,
    "aggregateRating": null,
    "alternativeHeadline": "Handhoneysuckle",
    "associatedMedia": null,
    "audience": null,
    "audio": null,
    "author": null,
    "award": "Crowwind",
    "character": null,
    "citation": null,
    "comment": null,
    "commentCount": 46,
    "contentLocation": null,
    "contentRating": "Shirttopaz",
    "contentReferenceTime": "2006-12-08T15:00",
    "contributor": null,
    "copyrightHolder": null,
    "copyrightYear": 6,
    "creator": null,
    "dateCreated": "1991-02-05",
    "dateModified": "1985-01-16",
    "datePublished": "1976-01-25",
    "discussionUrl": "Dartviolet",
    "editor": null,
    "educationalAlignment": null,
    "educationalUse": "Flasherfortune",
    "encoding": null,
    "exampleOfWork": null,
    "expires": "1995-04-02",
    "fileFormat": "Thundersky",
    "funder": null,
    "genre": "Queenglen",
    "hasPart": null,
    "headline": "Scaleriver",
    "inLanguage": null,
    "interactionStatistic": null,
    "interactivityType": "Tigerhoney",
    "isAccessibleForFree": true,
    "isBasedOn": null,
    "isFamilyFriendly": false,
    "isPartOf": null,
    "keywords": "Legendgentle",
    "learningResourceType": "Neckash",
    "license": null,
    "locationCreated": null,
    "mainEntity": null,
    "material": null,
    "mentions": null,
    "offers": null,
    "position": 2,
    "producer": null,
    "provider": null,
    "publication": null,
    "publisher": null,
    "publisherImprint": null,
    "publishingPrinciples": null,
    "recordedAt": null,
    "releasedEvent": null,
    "review": null,
    "schemaVersion": "Hawkmagenta",
    "sourceOrganization": null,
    "spatialCoverage": null,
    "sponsor": null,
    "temporalCoverage": "1996-08-31T18:28",
    "text": "Pegasusgrove",
    "thumbnailUrl": "Batluminous",
    "timeRequired": null,
    "translationOfWork": null,
    "translator": null,
    "typicalAgeRange": "Shiftsteel",
    "version": 23,
    "video": null,
    "workExample": null,
    "workTranslation": null
  },
  "name": "Walkerregal",
  "object": {
    "@type": "Thing",
    "additionalType": "Liftertwisty",
    "alternateName": "Howlerlinen",
    "description": "Centaurpitch",
    "disambiguatingDescription": "Ringerrogue",
    "identifier": null,
    "image": null,
    "mainEntityOfPage": null,
    "name": "Monkeyblossom",
    "potentialAction": null,
    "sameAs": "Boltstump",
    "url": "Hisspuzzle"
  },
  "participant": {
    "@type": "Organization",
    "actionableFeedbackPolicy": null,
    "address": null,
    "aggregateRating": null,
    "alumni": null,
    "areaServed": null,
    "award": "Pipersolstice",
    "brand": null,
    "contactPoint": null,
    "correctionsPolicy": null,
    "department": null,
    "dissolutionDate": "1972-02-08",
    "diversityPolicy": null,
    "duns": "Bootsteel",
    "email": "Choppernotch",
    "employee": null,
    "ethicsPolicy": null,
    "event": null,
    "faxNumber": "Gullpebble",
    "founder": null,
    "foundingDate": "1991-03-17",
    "foundingLocation": null,
    "funder": null,
    "globalLocationNumber": "Tailmad",
    "hasOfferCatalog": null,
    "hasPOS": null,
    "isicV4": "Witchpsychadelic",
    "legalName": "Huggermeadow",
    "leiCode": "Cloudbold",
    "location": null,
    "logo": null,
    "makesOffer": null,
    "member": null,
    "memberOf": null,
    "naics": "Thornbrave",
    "numberOfEmployees": null,
    "owns": null,
    "parentOrganization": null,
    "publishingPrinciples": null,
    "review": null,
    "seeks": null,
    "sponsor": null,
    "subOrganization": null,
    "taxID": "Tigerquiver",
    "telephone": "Owlsatin",
    "unnamedSourcesPolicy": null,
    "vatID": "Spidershine"
  },
  "potentialAction": {
    "@type": "Action",
    "actionStatus": null,
    "agent": null,
    "endTime": "1994-10-05T09:32",
    "error": null,
    "instrument": null,
    "location": null,
    "object": null,
    "participant": null,
    "result": null,
    "startTime": "2004-12-16T06:31",
    "target": null
  },
  "purpose": null,
  "result": {
    "@type": "Thing",
    "additionalType": "Chargertundra",
    "alternateName": "Graspmetal",
    "description": "Princeblack",
    "disambiguatingDescription": "Darthail",
    "identifier": null,
    "image": null,
    "mainEntityOfPage": null,
    "name": "Sargentbristle",
    "potentialAction": null,
    "sameAs": "Backcyber",
    "url": "Tailstream"
  },
  "sameAs": "Traderjuniper",
  "startTime": "2010-07-19T19:58",
  "target": {
    "@type": "EntryPoint",
    "actionApplication": null,
    "actionPlatform": "Catpink",
    "contentType": "Ladycarnation",
    "encodingType": "Banefantasy",
    "httpMethod": "Spikehollow",
    "urlTemplate": "Oxsquare"
  },
  "url": "Mythebony"
}
